funcall/__init__.py
funcall/decorators.py
funcall/funcall.py
funcall/metadata.py
funcall/params_to_schema.py
funcall/py.typed
funcall/types.py
funcall-0.10.0.dist-info/METADATA
funcall-0.10.0.dist-info/WHEEL
funcall-0.10.0.dist-info/RECORD
