Metadata-Version: 2.4
Name: funcall
Version: 0.10.0
Summary: A toolkit for function calling, tool registration, and LiteLLM & OpenAI compatible tool integration with sync/async support.
Author-email: Jianqi Pan <jannchie@gmail.com>
License: MIT
Keywords: AI,function call,openai,pydantic,rich,tooling
Classifier: Intended Audience :: Developers
Classifier: License :: OSI Approved :: MIT License
Classifier: Operating System :: OS Independent
Classifier: Programming Language :: Python :: 3
Classifier: Programming Language :: Python :: 3.10
Classifier: Programming Language :: Python :: 3.11
Classifier: Programming Language :: Python :: 3.12
Classifier: Topic :: Software Development :: Libraries :: Python Modules
Requires-Python: >=3.10
Requires-Dist: litellm>=1.72.6.post1
Requires-Dist: openai>=1.79.0
Requires-Dist: pydantic>=2.11.4
Requires-Dist: rich>=14.0.0
Requires-Dist: typing-inspect>=0.9.0
